dagit/__init__.py
dagit/py.typed
dagit/version.py
dagit-1.12.13.dist-info/licenses/LICENSE
dagit-1.12.13.dist-info/METADATA
dagit-1.12.13.dist-info/WHEEL
dagit-1.12.13.dist-info/entry_points.txt
dagit-1.12.13.dist-info/top_level.txt
dagit-1.12.13.dist-info/RECORD
