Metadata-Version: 2.4
Name: dagit
Version: 1.12.13
Summary: Web UI for dagster.
Home-page: https://github.com/dagster-io/dagster
Author: Dagster Labs
Author-email: hello@dagsterlabs.com
License: Apache-2.0
Classifier: Programming Language :: Python :: 3.10
Classifier: Programming Language :: Python :: 3.11
Classifier: Programming Language :: Python :: 3.12
Classifier: Programming Language :: Python :: 3.13
Classifier: Programming Language :: Python :: 3.14
Classifier: License :: OSI Approved :: Apache Software License
Classifier: Operating System :: OS Independent
Requires-Python: >=3.10,<3.15
License-File: LICENSE
Requires-Dist: dagster-webserver==1.12.13
Provides-Extra: notebook
Requires-Dist: dagster-webserver[notebook]==1.12.13; extra == "notebook"
Provides-Extra: test
Requires-Dist: dagster-webserver[test]==1.12.13; extra == "test"
Dynamic: author
Dynamic: author-email
Dynamic: classifier
Dynamic: description
Dynamic: description-content-type
Dynamic: home-page
Dynamic: license
Dynamic: license-file
Dynamic: provides-extra
Dynamic: requires-dist
Dynamic: requires-python
Dynamic: summary
